cranial/examples/README.md
cranial/examples/gensim_lda.ipynb
cranial/examples/w2v.ipynb
cranial/model_base.py
cranial/models/gensim_models.py
cranial/models/nlp.py
cranial/models/reporting.py
cranial/models/spacy_tokenizers.py
cranial/models/tests/data/dandelion_nex.json
cranial/models/tests/data/just_texts.txt
cranial/models/tests/test_gensim_models.py
cranial/models/tests/test_nlp.py
cranial/models/tests/test_spacy_tokenizers.py
cranial/models/tests/test_tokenizers.py
cranial/models/tokenizers.py
cranial/online_training.py
cranial/re_iter.py
cranial/records_wrapper.py
cranial/tests/test_cranial.py
cranial/tests/test_model_base.py
cranial/tests/test_online_learning.py
cranial/tests/test_re_iter.py
cranial/tests/test_re_iter_multiprocessing.py
cranial_modeling-0.2.0.dist-info/LICENSE
cranial_modeling-0.2.0.dist-info/WHEEL
cranial_modeling-0.2.0.dist-info/METADATA
cranial_modeling-0.2.0.dist-info/RECORD
